asyncio_tcp_message_228/__init__.py
asyncio_tcp_message_228/commands.py
asyncio_tcp_message_228/data.py
asyncio_tcp_message_228/dictionaries.py
asyncio_tcp_message_228/main.py
asyncio_tcp_message_228/validators.py
asyncio_tcp_message_228-0.1.1.dist-info/WHEEL
asyncio_tcp_message_228-0.1.1.dist-info/METADATA
asyncio_tcp_message_228-0.1.1.dist-info/RECORD
