Metadata-Version: 2.1
Name: asyncio-tcp-message-228
Version: 0.1.1
Summary: 
Author: eale
Author-email: novode25@gmail.com
Requires-Python: >=3.9,<4.0
Classifier: Programming Language :: Python :: 3
Classifier: Programming Language :: Python :: 3.10
Classifier: Programming Language :: Python :: 3.9
Requires-Dist: install (>=1.3.5,<2.0.0)
Requires-Dist: poetry (>=1.1.13,<2.0.0)
